{
  "script_id": "01001008",
  "title": "取成都",
  "genre": "历史剧",
  "nodes": [
    {
      "id": "c_刘璋",
      "name": "刘璋",
      "hangdang": "老生",
      "hangdang_coarse": "生",
      "is_main": true,
      "degree": 11,
      "weighted_degree": 117.0,
      "betweenness": 0.2182,
      "weighted_betweenness": 0.7091,
      "closeness": 1.0,
      "eigenvector": 0.6804,
      "community_id": 0
    },
    {
      "id": "c_刘备",
      "name": "刘备",
      "hangdang": "老生",
      "hangdang_coarse": "生",
      "is_main": true,
      "degree": 7,
      "weighted_degree": 52.0,
      "betweenness": 0.0,
      "weighted_betweenness": 0.1273,
      "closeness": 0.7333,
      "eigenvector": 0.4789,
      "community_id": 1
    },
    {
      "id": "c_刘玉",
      "name": "刘玉",
      "hangdang": "小生",
      "hangdang_coarse": "生",
      "is_main": true,
      "degree": 5,
      "weighted_degree": 31.0,
      "betweenness": 0.0,
      "weighted_betweenness": 0.0,
      "closeness": 0.6471,
      "eigenvector": 0.345,
      "community_id": 0
    },
    {
      "id": "c_王累",
      "name": "王累",
      "hangdang": "丑",
      "hangdang_coarse": "丑",
      "is_main": true,
      "degree": 5,
      "weighted_degree": 31.0,
      "betweenness": 0.0,
      "weighted_betweenness": 0.0,
      "closeness": 0.6471,
      "eigenvector": 0.3144,
      "community_id": 0
    },
    {
      "id": "c_诸葛亮",
      "name": "诸葛亮",
      "hangdang": "老生",
      "hangdang_coarse": "生",
      "is_main": false,
      "degree": 7,
      "weighted_degree": 27.0,
      "betweenness": 0.0,
      "weighted_betweenness": 0.0,
      "closeness": 0.7333,
      "eigenvector": 0.2288,
      "community_id": 1
    },
    {
      "id": "c_众人",
      "name": "众人",
      "hangdang": "老生",
      "hangdang_coarse": "生",
      "is_main": false,
      "degree": 11,
      "weighted_degree": 16.0,
      "betweenness": 0.2182,
      "weighted_betweenness": 0.0,
      "closeness": 1.0,
      "eigenvector": 0.0919,
      "community_id": 0
    },
    {
      "id": "c_马超",
      "name": "马超",
      "hangdang": "老生",
      "hangdang_coarse": "生",
      "is_main": true,
      "degree": 5,
      "weighted_degree": 15.0,
      "betweenness": 0.0,
      "weighted_betweenness": 0.0,
      "closeness": 0.6471,
      "eigenvector": 0.1441,
      "community_id": 0
    },
    {
      "id": "c_严颜",
      "name": "严颜",
      "hangdang": "老生",
      "hangdang_coarse": "生",
      "is_main": false,
      "degree": 7,
      "weighted_degree": 9.0,
      "betweenness": 0.0,
      "weighted_betweenness": 0.0,
      "closeness": 0.7333,
      "eigenvector": 0.0532,
      "community_id": 0
    },
    {
      "id": "c_赵云",
      "name": "赵云",
      "hangdang": "武生",
      "hangdang_coarse": "生",
      "is_main": false,
      "degree": 7,
      "weighted_degree": 7.0,
      "betweenness": 0.0,
      "weighted_betweenness": 0.0,
      "closeness": 0.7333,
      "eigenvector": 0.0289,
      "community_id": 2
    },
    {
      "id": "c_探子",
      "name": "探子",
      "hangdang": "武生",
      "hangdang_coarse": "生",
      "is_main": false,
      "degree": 5,
      "weighted_degree": 7.0,
      "betweenness": 0.0,
      "weighted_betweenness": 0.0,
      "closeness": 0.6471,
      "eigenvector": 0.0534,
      "community_id": 0
    },
    {
      "id": "c_魏延",
      "name": "魏延",
      "hangdang": "武生",
      "hangdang_coarse": "生",
      "is_main": false,
      "degree": 7,
      "weighted_degree": 7.0,
      "betweenness": 0.0,
      "weighted_betweenness": 0.0,
      "closeness": 0.7333,
      "eigenvector": 0.0289,
      "community_id": 3
    },
    {
      "id": "c_黄忠",
      "name": "黄忠",
      "hangdang": "老生",
      "hangdang_coarse": "生",
      "is_main": false,
      "degree": 7,
      "weighted_degree": 7.0,
      "betweenness": 0.0,
      "weighted_betweenness": 0.0,
      "closeness": 0.7333,
      "eigenvector": 0.0289,
      "community_id": 4
    }
  ],
  "links": [
    {
      "source": "c_刘备",
      "target": "c_刘璋",
      "weight": 34.0,
      "types": [
        "对话",
        "同场"
      ],
      "dialogue_count": 16,
      "normalized_weight": 1.0
    },
    {
      "source": "c_刘玉",
      "target": "c_刘璋",
      "weight": 27.0,
      "types": [
        "对话",
        "同场"
      ],
      "dialogue_count": 13,
      "normalized_weight": 0.7941
    },
    {
      "source": "c_刘璋",
      "target": "c_王累",
      "weight": 24.0,
      "types": [
        "对话",
        "同场"
      ],
      "dialogue_count": 11,
      "normalized_weight": 0.7059
    },
    {
      "source": "c_刘备",
      "target": "c_诸葛亮",
      "weight": 13.0,
      "types": [
        "对话",
        "同场"
      ],
      "dialogue_count": 6,
      "normalized_weight": 0.3824
    },
    {
      "source": "c_刘璋",
      "target": "c_马超",
      "weight": 10.0,
      "types": [
        "对话",
        "同场"
      ],
      "dialogue_count": 4,
      "normalized_weight": 0.2941
    },
    {
      "source": "c_刘璋",
      "target": "c_诸葛亮",
      "weight": 9.0,
      "types": [
        "对话",
        "同场"
      ],
      "dialogue_count": 4,
      "normalized_weight": 0.2647
    },
    {
      "source": "c_众人",
      "target": "c_刘璋",
      "weight": 4.0,
      "types": [
        "对话",
        "同场"
      ],
      "dialogue_count": 1,
      "normalized_weight": 0.1176
    },
    {
      "source": "c_严颜",
      "target": "c_刘璋",
      "weight": 3.0,
      "types": [
        "对话",
        "同场"
      ],
      "dialogue_count": 1,
      "normalized_weight": 0.0882
    },
    {
      "source": "c_众人",
      "target": "c_王累",
      "weight": 3.0,
      "types": [
        "对话",
        "同场"
      ],
      "dialogue_count": 1,
      "normalized_weight": 0.0882
    },
    {
      "source": "c_刘璋",
      "target": "c_探子",
      "weight": 3.0,
      "types": [
        "对话",
        "同场"
      ],
      "dialogue_count": 1,
      "normalized_weight": 0.0882
    },
    {
      "source": "c_王累",
      "target": "c_马超",
      "weight": 2.0,
      "types": [
        "同场"
      ],
      "dialogue_count": 0,
      "normalized_weight": 0.0588
    },
    {
      "source": "c_严颜",
      "target": "c_众人",
      "weight": 1.0,
      "types": [
        "同场"
      ],
      "dialogue_count": 0,
      "normalized_weight": 0.0294
    },
    {
      "source": "c_严颜",
      "target": "c_刘备",
      "weight": 1.0,
      "types": [
        "同场"
      ],
      "dialogue_count": 0,
      "normalized_weight": 0.0294
    },
    {
      "source": "c_严颜",
      "target": "c_诸葛亮",
      "weight": 1.0,
      "types": [
        "同场"
      ],
      "dialogue_count": 0,
      "normalized_weight": 0.0294
    },
    {
      "source": "c_严颜",
      "target": "c_赵云",
      "weight": 1.0,
      "types": [
        "同场"
      ],
      "dialogue_count": 0,
      "normalized_weight": 0.0294
    },
    {
      "source": "c_严颜",
      "target": "c_魏延",
      "weight": 1.0,
      "types": [
        "同场"
      ],
      "dialogue_count": 0,
      "normalized_weight": 0.0294
    },
    {
      "source": "c_严颜",
      "target": "c_黄忠",
      "weight": 1.0,
      "types": [
        "同场"
      ],
      "dialogue_count": 0,
      "normalized_weight": 0.0294
    },
    {
      "source": "c_众人",
      "target": "c_刘备",
      "weight": 1.0,
      "types": [
        "同场"
      ],
      "dialogue_count": 0,
      "normalized_weight": 0.0294
    },
    {
      "source": "c_众人",
      "target": "c_刘玉",
      "weight": 1.0,
      "types": [
        "同场"
      ],
      "dialogue_count": 0,
      "normalized_weight": 0.0294
    },
    {
      "source": "c_众人",
      "target": "c_探子",
      "weight": 1.0,
      "types": [
        "同场"
      ],
      "dialogue_count": 0,
      "normalized_weight": 0.0294
    },
    {
      "source": "c_众人",
      "target": "c_诸葛亮",
      "weight": 1.0,
      "types": [
        "同场"
      ],
      "dialogue_count": 0,
      "normalized_weight": 0.0294
    },
    {
      "source": "c_众人",
      "target": "c_赵云",
      "weight": 1.0,
      "types": [
        "同场"
      ],
      "dialogue_count": 0,
      "normalized_weight": 0.0294
    },
    {
      "source": "c_众人",
      "target": "c_马超",
      "weight": 1.0,
      "types": [
        "同场"
      ],
      "dialogue_count": 0,
      "normalized_weight": 0.0294
    },
    {
      "source": "c_众人",
      "target": "c_魏延",
      "weight": 1.0,
      "types": [
        "同场"
      ],
      "dialogue_count": 0,
      "normalized_weight": 0.0294
    },
    {
      "source": "c_众人",
      "target": "c_黄忠",
      "weight": 1.0,
      "types": [
        "同场"
      ],
      "dialogue_count": 0,
      "normalized_weight": 0.0294
    },
    {
      "source": "c_刘备",
      "target": "c_赵云",
      "weight": 1.0,
      "types": [
        "同场"
      ],
      "dialogue_count": 0,
      "normalized_weight": 0.0294
    },
    {
      "source": "c_刘备",
      "target": "c_魏延",
      "weight": 1.0,
      "types": [
        "同场"
      ],
      "dialogue_count": 0,
      "normalized_weight": 0.0294
    },
    {
      "source": "c_刘备",
      "target": "c_黄忠",
      "weight": 1.0,
      "types": [
        "同场"
      ],
      "dialogue_count": 0,
      "normalized_weight": 0.0294
    },
    {
      "source": "c_刘玉",
      "target": "c_探子",
      "weight": 1.0,
      "types": [
        "同场"
      ],
      "dialogue_count": 0,
      "normalized_weight": 0.0294
    },
    {
      "source": "c_刘玉",
      "target": "c_王累",
      "weight": 1.0,
      "types": [
        "同场"
      ],
      "dialogue_count": 0,
      "normalized_weight": 0.0294
    },
    {
      "source": "c_刘玉",
      "target": "c_马超",
      "weight": 1.0,
      "types": [
        "同场"
      ],
      "dialogue_count": 0,
      "normalized_weight": 0.0294
    },
    {
      "source": "c_刘璋",
      "target": "c_赵云",
      "weight": 1.0,
      "types": [
        "同场"
      ],
      "dialogue_count": 0,
      "normalized_weight": 0.0294
    },
    {
      "source": "c_刘璋",
      "target": "c_魏延",
      "weight": 1.0,
      "types": [
        "同场"
      ],
      "dialogue_count": 0,
      "normalized_weight": 0.0294
    },
    {
      "source": "c_刘璋",
      "target": "c_黄忠",
      "weight": 1.0,
      "types": [
        "同场"
      ],
      "dialogue_count": 0,
      "normalized_weight": 0.0294
    },
    {
      "source": "c_探子",
      "target": "c_王累",
      "weight": 1.0,
      "types": [
        "同场"
      ],
      "dialogue_count": 0,
      "normalized_weight": 0.0294
    },
    {
      "source": "c_探子",
      "target": "c_马超",
      "weight": 1.0,
      "types": [
        "同场"
      ],
      "dialogue_count": 0,
      "normalized_weight": 0.0294
    },
    {
      "source": "c_诸葛亮",
      "target": "c_赵云",
      "weight": 1.0,
      "types": [
        "同场"
      ],
      "dialogue_count": 0,
      "normalized_weight": 0.0294
    },
    {
      "source": "c_诸葛亮",
      "target": "c_魏延",
      "weight": 1.0,
      "types": [
        "同场"
      ],
      "dialogue_count": 0,
      "normalized_weight": 0.0294
    },
    {
      "source": "c_诸葛亮",
      "target": "c_黄忠",
      "weight": 1.0,
      "types": [
        "同场"
      ],
      "dialogue_count": 0,
      "normalized_weight": 0.0294
    },
    {
      "source": "c_赵云",
      "target": "c_魏延",
      "weight": 1.0,
      "types": [
        "同场"
      ],
      "dialogue_count": 0,
      "normalized_weight": 0.0294
    },
    {
      "source": "c_赵云",
      "target": "c_黄忠",
      "weight": 1.0,
      "types": [
        "同场"
      ],
      "dialogue_count": 0,
      "normalized_weight": 0.0294
    },
    {
      "source": "c_魏延",
      "target": "c_黄忠",
      "weight": 1.0,
      "types": [
        "同场"
      ],
      "dialogue_count": 0,
      "normalized_weight": 0.0294
    }
  ],
  "metrics": {
    "node_count": 12,
    "edge_count": 42,
    "density": 0.6364,
    "avg_clustering": 0.9273,
    "avg_degree": 7.0,
    "avg_weighted_degree": 27.17,
    "component_count": 1,
    "avg_weighted_clustering": 0.0613,
    "modularity": 0.0605,
    "assortativity_hangdang": -0.0633,
    "main_subgraph": {
      "node_count": 5,
      "edge_count": 7,
      "density": 0.7,
      "avg_clustering": 0.1199,
      "modularity": 0.0
    }
  }
}
